{"answer_user_img": "https://ossimg.xinli001.com/20181023/2bfd867bdb4b3f814f73b550c16b31e8.png!80", "answer_user_name": "小飞龙妈妈", "answer_content": "\n                            我突然注意到你说，虽然你学历不高，但是“身边一堆高学历有能力的人”，这是为啥呢？能否说明你虽然学历不高，但是已经混迹在高学历的人群当中了？那相比较和你学历相同或者相当的人，是否说明你已经非常非常出色了呢？<br />\n<br />\n另外，我感觉你比较在意“学历”，但这事儿真不能怪你，因为从小到大，周围对我们的评价标准就比较单一。现在就连小学生都知道，我跳绳不好没事，眼睛近视了没事，只要我学习好就行。我们从小就被“引导”着只关注这唯一的领域。<br />\n<br />\n我有段时间和一群90后舞蹈老师混迹在一起。我发现了一个特点，那就是：他们这群舞蹈老师吧，根本不能用“这类人”或“这群人”来概括，只能用“这个人”或“那个人”来说。为啥呢？因为他们别管是谁，都和其他任何人都不太一样，甚至连一丝重叠的特点都找不到，一个是一个的，而不是一类一类、一群一群的。<br />\n<br />\n我想原因之一可能在于，他们学舞蹈的孩子，早早的就住校了，他们的少年期、青春期、青年期，甚至是儿童期，都没有被“修理”过，没有一个统一的标准去卡他们，去要求他们。<br />\n<br />\n舞蹈这个东西，一台剧，一个动作，一个角色，没有统一的标准要求，必须做到什么程度，才是美的，才是好的，没说哪个角色就一定是好的，或者坏的。你适合这个，她适合那个，所以他们每个人都不一样，活得特别痛快的感觉。<br />\n<br />\n我想，当衡量一群人的标准，只有唯一一个的时候，就会让我们多数人感到焦虑。好在现在已经有不少人开始不那么在意那唯一的一个衡量标准了，也有越来越多的“小众群体”出现并被关注到了。相信越来越多元化的社会，会让我们每个人都有尽情绽放自己的园地。<br />\n<br />\n相信，你也可以！                        ", "answer_digg": "0", "answer_push_time": "1小时前"}
